memethesis/__init__.py
memethesis/__main__.py
memethesis/fancyprint.py
memethesis/fonts.py
memethesis/format_utils.py
memethesis/help.txt
memethesis/interactive.py
memethesis/memethesizers.py
memethesis/meme/__init__.py
memethesis/meme/caption.py
memethesis/meme/horizontal.py
memethesis/meme/imageops.py
memethesis/meme/separator.py
memethesis/meme/single.py
memethesis/meme/textops.py
memethesis/meme/vertical.py
memethesis/meme/res/fonts/ComicSans.ttf
memethesis/meme/res/fonts/Impact.ttf
memethesis/meme/res/fonts/NotoSans-Regular.ttf
memethesis/meme/res/fonts/NotoSansMono-Regular.ttf
memethesis/meme/res/template/brainsize/brain1.jpg
memethesis/meme/res/template/brainsize/brain10.jpg
memethesis/meme/res/template/brainsize/brain11.jpg
memethesis/meme/res/template/brainsize/brain12.jpg
memethesis/meme/res/template/brainsize/brain13.jpg
memethesis/meme/res/template/brainsize/brain14.jpg
memethesis/meme/res/template/brainsize/brain2.jpg
memethesis/meme/res/template/brainsize/brain3.jpg
memethesis/meme/res/template/brainsize/brain4.jpg
memethesis/meme/res/template/brainsize/brain5.jpg
memethesis/meme/res/template/brainsize/brain6.jpg
memethesis/meme/res/template/brainsize/brain7.jpg
memethesis/meme/res/template/brainsize/brain8.jpg
memethesis/meme/res/template/brainsize/brain9.jpg
memethesis/meme/res/template/brainsize/format.yml
memethesis/meme/res/template/drake/drake_dislike.jpg
memethesis/meme/res/template/drake/drake_like.jpg
memethesis/meme/res/template/drake/format.yml
memethesis/meme/res/template/draw25/draw_25_or_do_sth.jpg
memethesis/meme/res/template/draw25/format.yml
memethesis/meme/res/template/onefear/format.yml
memethesis/meme/res/template/onefear/onefear.jpg
memethesis/meme/res/template/pigeon/format.yml
memethesis/meme/res/template/pigeon/is_this_a_pigeon.jpg
memethesis/meme/res/template/pooh/format.yml
memethesis/meme/res/template/pooh/tired.jpg
memethesis/meme/res/template/pooh/wired.jpg
memethesis/meme/res/template/womanyelling/catto.jpg
memethesis-3.2.1.dist-info/LICENSE
memethesis-3.2.1.dist-info/METADATA
memethesis-3.2.1.dist-info/WHEEL
memethesis-3.2.1.dist-info/entry_points.txt
memethesis-3.2.1.dist-info/top_level.txt
memethesis-3.2.1.dist-info/RECORD
