Metadata-Version: 2.1
Name: memethesis
Version: 3.2.1
Summary: A CLI tool to visualize your memes
Home-page: https://github.com/fakefred/memethesis-cli
Author: fakefred
Author-email: fakefred@protonmail.ch
License: GPLv3
Project-URL: LiberaPay, https://liberapay.com/fakefred/donate
Keywords: meme
Platform: UNKNOWN
Classifier: Development Status :: 4 - Beta
Classifier: Intended Audience :: End Users/Desktop
Classifier: License :: OSI Approved :: GNU General Public License v3 (GPLv3)
Classifier: Natural Language :: English
Classifier: Topic :: Multimedia :: Graphics
Requires-Python: >=3.5
Requires-Dist: PyYAML (>=5.1)
Requires-Dist: Pillow
Requires-Dist: PyInquirer
Requires-Dist: colored
